easynotify/__init__.py
easynotify/notifier.py
easynotify_sachin-1.1.0.dist-info/METADATA
easynotify_sachin-1.1.0.dist-info/WHEEL
easynotify_sachin-1.1.0.dist-info/top_level.txt
easynotify_sachin-1.1.0.dist-info/RECORD
