Metadata-Version: 2.4
Name: easynotify-sachin
Version: 1.1.0
Summary: A simple notification helper for AWS SNS or email.
Author: Sachin Rendla
Author-email: sachin@nci.com
Requires-Python: >=3.6
Requires-Dist: boto3
Dynamic: author
Dynamic: author-email
Dynamic: requires-dist
Dynamic: requires-python
Dynamic: summary
